healthyhouse_api/__init__.py
healthyhouse_api/healthyhouse_api.py
healthyhouse_api/import_orders.py
healthyhouse_api/import_results.py
healthyhouse_api-0.3.0.dist-info/DESCRIPTION.rst
healthyhouse_api-0.3.0.dist-info/METADATA
healthyhouse_api-0.3.0.dist-info/RECORD
healthyhouse_api-0.3.0.dist-info/WHEEL
healthyhouse_api-0.3.0.dist-info/entry_points.txt
healthyhouse_api-0.3.0.dist-info/metadata.json
healthyhouse_api-0.3.0.dist-info/top_level.txt
