Metadata-Version: 2.0
Name: healthyhouse-api
Version: 0.3.0
Summary: A wrapper of the RESTful API service available for a healthyhouse installation
Home-page: https://github.com/bsdis/healthyhouse_api
Author: Healthyhouse
Author-email: info@radonmeters.com
License: MIT license
Keywords: healthyhouse_api
Platform: UNKNOWN
Classifier: Development Status :: 2 - Pre-Alpha
Classifier: Intended Audience :: Developers
Classifier: License :: OSI Approved :: MIT License
Classifier: Natural Language :: English
Classifier: Programming Language :: Python :: 2
Classifier: Programming Language :: Python :: 2.7
Classifier: Programming Language :: Python :: 3
Classifier: Programming Language :: Python :: 3.4
Classifier: Programming Language :: Python :: 3.5
Classifier: Programming Language :: Python :: 3.6
Requires-Dist: requests
Requires-Dist: marshmallow
Requires-Dist: pandas
